.coveragerc
.gitignore
.travis.yml
CHANGES.rst
CONTRIBUTORS.rst
MANIFEST.in
README.rst
TODO.txt
bootstrap.py
buildout.cfg
requirements.txt
setup.py
travis.cfg
buildout.d/base.cfg
buildout.d/checkouts.cfg
buildout.d/development.cfg
buildout.d/jenkins.cfg
buildout.d/sources.cfg
buildout.d/versions.cfg
docs/LICENSE.GPL
docs/LICENSE.rst
src/collective/__init__.py
src/collective.contact.duplicated.egg-info/PKG-INFO
src/collective.contact.duplicated.egg-info/SOURCES.txt
src/collective.contact.duplicated.egg-info/dependency_links.txt
src/collective.contact.duplicated.egg-info/entry_points.txt
src/collective.contact.duplicated.egg-info/namespace_packages.txt
src/collective.contact.duplicated.egg-info/not-zip-safe
src/collective.contact.duplicated.egg-info/requires.txt
src/collective.contact.duplicated.egg-info/top_level.txt
src/collective/contact/__init__.py
src/collective/contact/duplicated/__init__.py
src/collective/contact/duplicated/api.py
src/collective/contact/duplicated/configure.zcml
src/collective/contact/duplicated/fields.py
src/collective/contact/duplicated/fields.zcml
src/collective/contact/duplicated/interfaces.py
src/collective/contact/duplicated/setuphandlers.py
src/collective/contact/duplicated/testing.py
src/collective/contact/duplicated/testing.zcml
src/collective/contact/duplicated/browser/__init__.py
src/collective/contact/duplicated/browser/configure.zcml
src/collective/contact/duplicated/browser/view.py
src/collective/contact/duplicated/browser/contactfaceted/__init__.py
src/collective/contact/duplicated/browser/contactfaceted/action.py
src/collective/contact/duplicated/browser/contactfaceted/configure.zcml
src/collective/contact/duplicated/browser/static/duplicated.css
src/collective/contact/duplicated/browser/static/duplicated.js
src/collective/contact/duplicated/browser/templates/compare.pt
src/collective/contact/duplicated/locales/collective.contact.duplicated.pot
src/collective/contact/duplicated/locales/update.sh
src/collective/contact/duplicated/locales/fr/LC_MESSAGES/collective.contact.duplicated.po
src/collective/contact/duplicated/profiles/default/browserlayer.xml
src/collective/contact/duplicated/profiles/default/collectivecontactduplicated_marker.txt
src/collective/contact/duplicated/profiles/default/cssregistry.xml
src/collective/contact/duplicated/profiles/default/jsregistry.xml
src/collective/contact/duplicated/profiles/default/metadata.xml
