Metadata-Version: 2.1
Name: collective.contact.duplicated
Version: 0.6
Summary: Tools to manage duplicated contacts
Home-page: http://pypi.python.org/pypi/collective.contact.duplicated
Author: Thomas Desvenain
Author-email: thomas.desvenain@gmail.com
License: GPL
Keywords: contacts
Platform: UNKNOWN
Classifier: Environment :: Web Environment
Classifier: Framework :: Plone
Classifier: Framework :: Plone :: 4.3
Classifier: Programming Language :: Python
Classifier: Programming Language :: Python :: 2.7
Provides-Extra: test
